{
    "q1": [
        "C",
        "D",
        "E"
    ],
    "q2": [
        "C",
        "D"
    ],
    "q3": [
        "C",
        "D",
        "E"
    ],
    "q4": [
        "A",
        "C",
        "E"
    ],
    "q5": [
        "B"
    ],
    "q6": [
        "B",
        "D"
    ],
    "q7": [
        "A",
        "B",
        "C",
        "D"
    ],
    "q8": [
        "D"
    ],
    "q9": [
        "B",
        "E"
    ],
    "q10": [
        "D"
    ],
    "q11": [
        "C",
        "D",
        "E"
    ],
    "q12": [
        "C",
        "D",
        "E"
    ],
    "q13": [
        "C",
        "E"
    ],
    "q14": [
        "A",
        "B",
        "D"
    ],
    "q15": [
        "C",
        "E"
    ],
    "q16": [
        "B",
        "E"
    ],
    "q17": [
        "A",
        "C",
        "D"
    ],
    "q18": [
        "A",
        "E"
    ],
    "q19": [
        "B",
        "D"
    ],
    "q20": [
        "A",
        "C",
        "D",
        "E"
    ],
    "q21": [
        "A",
        "E"
    ],
    "q22": [
        "B",
        "E"
    ],
    "q23": [
        "D",
        "E"
    ],
    "q24": [
        "A",
        "B",
        "C"
    ],
    "q25": [
        "A",
        "B",
        "D",
        "E"
    ],
    "q26": [
        "A",
        "B",
        "C"
    ],
    "q27": [
        "A",
        "B",
        "E"
    ],
    "q28": [
        "A",
        "E"
    ],
    "q29": [
        "A",
        "D",
        "E"
    ],
    "q30": [
        "B",
        "C",
        "D"
    ],
    "q31": [
        "A",
        "C",
        "D",
        "E"
    ],
    "q32": [
        "B",
        "D",
        "E"
    ],
    "q33": [
        "A",
        "C"
    ],
    "q34": [
        "B",
        "C",
        "D",
        "E"
    ],
    "q35": [
        "B",
        "C",
        "D"
    ],
    "q36": [
        "B"
    ],
    "q37": [
        "A",
        "D"
    ],
    "q38": [
        "B",
        "D",
        "E"
    ],
    "q39": [
        "A",
        "C",
        "D",
        "E"
    ],
    "q40": [
        "E"
    ],
    "q41": [
        "B"
    ],
    "q42": [
        "A"
    ],
    "q43": [
        "C"
    ],
    "q44": [
        "C"
    ]
}