{
    "q1": [
        "A"
    ],
    "q2": [
        "A",
        "B"
    ],
    "q3": [
        "A",
        "C"
    ],
    "q4": [
        "B"
    ],
    "q5": [
        "C"
    ],
    "q6": [
        "D"
    ],
    "q7": [
        "A",
        "B",
        "C"
    ],
    "q8": [
        "C"
    ],
    "q9": [
        "C"
    ],
    "q10": [
        "B"
    ],
    "q11": [
        "B"
    ],
    "q12": [
        "C",
        "E"
    ],
    "q13": [
        "B"
    ],
    "q14": [
        "B"
    ],
    "q15": [
        "D"
    ],
    "q16": [
        "D"
    ],
    "q17": [
        "D"
    ],
    "q18": [
        "A"
    ],
    "q19": [
        "D"
    ],
    "q20": [
        "E"
    ],
    "q21": [
        "B",
        "C",
        "E"
    ],
    "q22": [
        "B",
        "C",
        "D"
    ],
    "q23": [
        "A",
        "C",
        "E"
    ],
    "q24": [
        "A",
        "C",
        "D",
        "E"
    ],
    "q25": [
        "A",
        "B",
        "D",
        "E"
    ]
}